pass_audit/__init__.py
pass_audit/__main__.py
pass_audit/audit.py
pass_audit/msg.py
pass_audit/passwordstore.py
usr/lib/password-store/extensions/audit.bash
usr/share/bash-completion/completions/pass-audit
usr/share/man/man1/pass-audit.1
usr/share/zsh/site-functions/_pass-audit
pass_audit-1.2.dist-info/LICENSE
pass_audit-1.2.dist-info/METADATA
pass_audit-1.2.dist-info/WHEEL
pass_audit-1.2.dist-info/top_level.txt
pass_audit-1.2.dist-info/zip-safe
pass_audit-1.2.dist-info/RECORD
