Metadata-Version: 2.1
Name: pass-audit
Version: 1.2
Summary: A pass extension for auditing your password repository.
Home-page: https://github.com/roddhjav/pass-audit
Author: Alexandre Pujol
Author-email: alexandre@pujol.io
License: GPL3
Project-URL: Documentation, https://github.com/roddhjav/pass-audit
Project-URL: Source, https://github.com/roddhjav/pass-audit
Project-URL: Issues, https://github.com/roddhjav/pass-audit/issues
Project-URL: Changelog, https://github.com/roddhjav/pass-audit/blob/master/CHANGELOG.md
Keywords: password-store,password,pass,pass-extension,audit,password-audit,haveibeenpwned
Platform: UNKNOWN
Classifier: Development Status :: 5 - Production/Stable
Classifier: Environment :: Console
Classifier: Intended Audience :: End Users/Desktop
Classifier: License :: OSI Approved :: GNU General Public License v3 or later (GPLv3+)
Classifier: Operating System :: MacOS :: MacOS X
Classifier: Operating System :: POSIX
Classifier: Operating System :: POSIX :: BSD
Classifier: Operating System :: POSIX :: Linux
Classifier: Operating System :: Microsoft :: Windows
Classifier: Programming Language :: Python
Classifier: Programming Language :: Python :: 3
Classifier: Programming Language :: Python :: 3 :: Only
Classifier: Programming Language :: Python :: 3.6
Classifier: Programming Language :: Python :: 3.7
Classifier: Programming Language :: Python :: 3.8
Classifier: Programming Language :: Python :: 3.9
Classifier: Programming Language :: Python :: 3.10
Classifier: Topic :: Security :: Cryptography
Requires-Python: >=3.6
License-File: LICENSE
Requires-Dist: requests
Requires-Dist: zxcvbn
